bitbutter/__init__.py
bitbutter/auth.py
bitbutter/client.py
bitbutter/compat.py
bitbutter/error.py
bitbutter/util.py
chainbridge-1.1.5.dist-info/METADATA
chainbridge-1.1.5.dist-info/RECORD
chainbridge-1.1.5.dist-info/WHEEL
chainbridge-1.1.5.dist-info/top_level.txt
