Metadata-Version: 2.1
Name: chainbridge
Version: 1.1.5
Summary: Bitbutter API client library
Home-page: https://github.com/polyledger/chainbridge/
Author: Matthew Rosendin
Author-email: matthew@polyledger.com
License: MIT
Download-URL: https://github.com/polyledger/chainbridge/tarball/1.1.5
Keywords: api,bitbutter,client
Platform: UNKNOWN
Classifier: Intended Audience :: Developers
Classifier: License :: OSI Approved :: Mozilla Public License 2.0 (MPL 2.0)
Classifier: Operating System :: OS Independent
Classifier: Programming Language :: Python :: 3.4
Classifier: Programming Language :: Python :: 3.5
Classifier: Programming Language :: Python :: 3.6
Classifier: Programming Language :: Python
Classifier: Topic :: Software Development :: Libraries :: Python Modules
Requires-Dist: requests (==2.13)
Requires-Dist: six (>=1.9)
Requires-Dist: pycrypto (>=2.6.1)
